di/__init__.py
di/di.py
di/di_container.py
di4injector-0.0.2.dist-info/METADATA
di4injector-0.0.2.dist-info/WHEEL
di4injector-0.0.2.dist-info/top_level.txt
di4injector-0.0.2.dist-info/RECORD
