Metadata-Version: 2.1
Name: di4injector
Version: 0.0.2
Summary: DI for injector
Home-page: https://github.com/gtaiyou24/di4injector
Author: taiyo tamura
Author-email: gtaiyou24@gmail.com
Requires-Dist: injector ==0.22.0
